kerl
